ado_client.py
config.py
jira_client.py
mcp_main.py
mcp_tools.py
mcp_traceability_tools.py
traceability_manager.py
vector_service.py
alm_traceability_mcp-1.0.6.dist-info/METADATA
alm_traceability_mcp-1.0.6.dist-info/WHEEL
alm_traceability_mcp-1.0.6.dist-info/entry_points.txt
alm_traceability_mcp-1.0.6.dist-info/top_level.txt
alm_traceability_mcp-1.0.6.dist-info/RECORD
