Metadata-Version: 2.4
Name: alm-traceability-mcp
Version: 1.0.6
Summary: ALM Traceability MCP Tools - Azure DevOps, Jira, and Vector Search integration
Author: Mridula
Author-email: Mridula <mridulait67@gmail.com>
License: MIT
Project-URL: Homepage, https://github.com/Vk171127/mcp-server-for-alm-tools
Project-URL: Repository, https://github.com/Vk171127/mcp-server-for-alm-tools
Project-URL: Issues, https://github.com/Vk171127/mcp-server-for-alm-tools/issues
Keywords: mcp,alm,traceability,azure-devops,jira,testing,ai,test-generation
Classifier: Development Status :: 4 - Beta
Classifier: Intended Audience :: Developers
Classifier: License :: OSI Approved :: MIT License
Classifier: Programming Language :: Python :: 3
Classifier: Programming Language :: Python :: 3.8
Classifier: Programming Language :: Python :: 3.9
Classifier: Programming Language :: Python :: 3.10
Classifier: Programming Language :: Python :: 3.11
Classifier: Programming Language :: Python :: 3.12
Classifier: Topic :: Software Development :: Testing
Classifier: Topic :: Software Development :: Quality Assurance
Requires-Python: >=3.8
Requires-Dist: mcp>=1.0.0
Requires-Dist: aiohttp>=3.9.0
Requires-Dist: pydantic>=2.5.0
Requires-Dist: python-dotenv>=1.0.0
Requires-Dist: asyncpg>=0.29.0
Requires-Dist: psycopg2-binary>=2.9.9
Requires-Dist: structlog>=23.1.0
Provides-Extra: vector
Requires-Dist: google-cloud-aiplatform; extra == "vector"
Requires-Dist: sentence-transformers; extra == "vector"
Provides-Extra: dev
Requires-Dist: pytest>=7.4.0; extra == "dev"
Requires-Dist: pytest-asyncio>=0.21.0; extra == "dev"
Requires-Dist: black; extra == "dev"
Requires-Dist: isort; extra == "dev"
Requires-Dist: flake8; extra == "dev"
Dynamic: author
Dynamic: requires-python
